{"query_time_annotations": [{"start_time": 2.554195011, "end_time": 12.445895691, "id": 1, "type": "3.5-bar occurrence with gaps"}, {"start_time": 2.554195011, "end_time": 13.746213152, "id": 2, "type": "occurrence"}, {"start_time": 13.746213152, "end_time": 23.730793651, "id": 1}, {"start_time": 13.746213152, "end_time": 25.031111111, "id": 2}, {"start_time": 24.984671202, "end_time": 34.876371882, "id": 1}, {"start_time": 25.031111111, "end_time": 36.31600907, "id": 2}, {"start_time": 36.269569161, "end_time": 47.461587302, "id": 2}, {"start_time": 36.31600907, "end_time": 46.114829932, "id": 1}, {"start_time": 47.461587302, "end_time": 57.399727892, "id": 1}, {"start_time": 47.461587302, "end_time": 58.607165533, "id": 2}, {"start_time": 58.607165533, "end_time": 68.591746032, "id": 1}, {"start_time": 58.607165533, "end_time": 69.938503401, "id": 2}, {"start_time": 69.938503401, "end_time": 79.783764172, "id": 1}, {"start_time": 69.938503401, "end_time": 81.26984126900001, "id": 2}, {"start_time": 81.26984127, "end_time": 91.254421769, "id": 1}, {"start_time": 81.26984127, "end_time": 92.368979592, "id": 2}, {"start_time": 92.368979592, "end_time": 102.260680272, "id": 1}, {"start_time": 92.368979592, "end_time": 103.65387755100001, "id": 2}, {"start_time": 103.653877551, "end_time": 113.592018141, "id": 1}, {"start_time": 103.653877551, "end_time": 114.985215419, "id": 2}, {"start_time": 114.98521542, "end_time": 124.8769161, "id": 1}, {"start_time": 114.98521542, "end_time": 126.084353742, "id": 2}, {"start_time": 126.084353741, "end_time": 136.115374149, "id": 1}, {"start_time": 126.084353741, "end_time": 137.322811791, "id": 2}, {"start_time": 137.322811791, "end_time": 147.35383219899998, "id": 1}, {"start_time": 137.322811791, "end_time": 148.700589569, "id": 2}, {"start_time": 148.700589569, "end_time": 158.59229024899997, "id": 1}, {"start_time": 148.700589569, "end_time": 159.93904761899998, "id": 2}, {"start_time": 159.939047619, "end_time": 169.970068027, "id": 1}, {"start_time": 159.939047619, "end_time": 171.13106576, "id": 2}, {"start_time": 171.13106576, "end_time": 181.11564625900002, "id": 1}, {"start_time": 171.177505669, "end_time": 182.3230839, "id": 2}, {"start_time": 182.288253968, "end_time": 193.584761905, "id": 2}, {"start_time": 182.3230839, "end_time": 192.307664399, "id": 1}, {"start_time": 193.56154195, "end_time": 203.59256235799998, "id": 1}, {"start_time": 193.584761905, "end_time": 205.04380952399998, "id": 2}, {"start_time": 204.985759637, "end_time": 214.877460317, "id": 1}, {"start_time": 205.043809524, "end_time": 216.177777778, "id": 2}, {"start_time": 216.03845805, "end_time": 226.069478458, "id": 1}, {"start_time": 216.177777778, "end_time": 227.393015873, "id": 2}, {"start_time": 227.323356009, "end_time": 237.215056689, "id": 1}, {"start_time": 227.393015873, "end_time": 238.526984127, "id": 2}, {"start_time": 238.46893424, "end_time": 240.001451247, "id": 0, "type": "partial occurrence"}], "target_time_annotations": [{"start_time": 0.371519274, "end_time": 9.705941043000001, "id": 1, "type": "3.5-bar occurrence with gaps"}, {"start_time": 0.371519274, "end_time": 11.006258503, "id": 2, "type": "occurrence"}], "target_track_id": "T040", "query_track_id": "T039", "sample_id": "S023", "description": "L1 gives original 3.5-bar sample, with gaps. L2 extends this to a 4-bar sample. Please note the last couple of beats of the original 4-bar sequence are different to what is heard in the sample track which is why I gave both versions \u2013 L1 has gaps on the sample track between every occurrence whereas L2 has no gaps. L0 gives the partial sample heard at the end."}