{"query_time_annotations": [{"start_time": 13.142494331, "end_time": 24.42739229, "id": 1, "type": "occurrence"}, {"start_time": 24.42739229, "end_time": 35.990929705, "id": 1}, {"start_time": 35.990929705, "end_time": 47.461587301, "id": 1}, {"start_time": 47.508027211, "end_time": 59.071564626, "id": 1}, {"start_time": 59.071564626, "end_time": 70.44934240399999, "id": 1}, {"start_time": 70.495782313, "end_time": 81.82712018100001, "id": 1}, {"start_time": 81.92, "end_time": 93.437097506, "id": 1}, {"start_time": 93.483537415, "end_time": 104.954195011, "id": 1}, {"start_time": 104.954195011, "end_time": 116.471292517, "id": 1}, {"start_time": 116.471292517, "end_time": 120.743764172, "id": 2, "type": "partial occurrence"}, {"start_time": 124.18031746, "end_time": 127.849070294, "id": 2}, {"start_time": 127.849070295, "end_time": 139.36616780100002, "id": 1}, {"start_time": 139.3661678, "end_time": 150.790385487, "id": 1}, {"start_time": 150.836825397, "end_time": 162.26104308400002, "id": 1}, {"start_time": 162.307482993, "end_time": 173.685260771, "id": 1}, {"start_time": 173.73170068, "end_time": 185.20235827599998, "id": 1}, {"start_time": 185.295238095, "end_time": 196.719455782, "id": 1}, {"start_time": 196.765895692, "end_time": 208.23655328799998, "id": 1}, {"start_time": 208.190113379, "end_time": 219.660770975, "id": 1}, {"start_time": 219.707210884, "end_time": 231.17786848, "id": 1}, {"start_time": 231.270748299, "end_time": 242.694965986, "id": 1}, {"start_time": 242.741405896, "end_time": 254.119183674, "id": 1}, {"start_time": 254.119183673, "end_time": 262.942766439, "id": 2}], "target_time_annotations": [{"start_time": 6.455147392, "end_time": 18.715283446, "id": 1, "type": "occurrence"}], "target_track_id": "T068", "query_track_id": "T069", "sample_id": "S041", "description": "L1 presence, L2 partial presence (not entire sample)"}